djangomockingbird/__init__.py
djangomockingbird/decorator.py
djangomockingbird/decorator_utils.py
djangomockingbird/make_mocks.py
djangomockingbird/queryset.py
djangomockingbird/queryset_utils.py
djangomockingbird/utils.py
djangomockingbird-1.0.9.dist-info/LICENSE
djangomockingbird-1.0.9.dist-info/WHEEL
djangomockingbird-1.0.9.dist-info/METADATA
djangomockingbird-1.0.9.dist-info/RECORD
