Metadata-Version: 2.1
Name: djangomockingbird
Version: 1.0.9
Summary: The fastest way to write the fastest Django unit tests
Home-page: https://github.com/larsvonschaff/Django-mockingbird
License: MIT
Keywords: django,testing
Author: larsvonschaff
Author-email: larsvonschaff@gmail.com
Requires-Python: >=3.7,<4.0
Classifier: License :: OSI Approved :: MIT License
Classifier: Programming Language :: Python :: 3
Classifier: Programming Language :: Python :: 3.10
Classifier: Programming Language :: Python :: 3.7
Classifier: Programming Language :: Python :: 3.8
Classifier: Programming Language :: Python :: 3.9
Requires-Dist: black (>=21.0)
Requires-Dist: django (>=2.2,<5)
Project-URL: Repository, https://github.com/larsvonschaff/Django-mockingbird
